isab_pytorch/__init__.py
isab_pytorch/isab_pytorch.py
isab_pytorch-0.2.3.dist-info/LICENSE
isab_pytorch-0.2.3.dist-info/METADATA
isab_pytorch-0.2.3.dist-info/WHEEL
isab_pytorch-0.2.3.dist-info/top_level.txt
isab_pytorch-0.2.3.dist-info/RECORD
