Metadata-Version: 2.1
Name: isab-pytorch
Version: 0.2.3
Summary: Induced Set Attention Block - Pytorch
Home-page: https://github.com/lucidrains/isab-pytorch
Author: Phil Wang
Author-email: lucidrains@gmail.com
License: MIT
Keywords: artificial intelligence,attention mechanism
Classifier: Development Status :: 4 - Beta
Classifier: Intended Audience :: Developers
Classifier: Topic :: Scientific/Engineering :: Artificial Intelligence
Classifier: License :: OSI Approved :: MIT License
Classifier: Programming Language :: Python :: 3.6
License-File: LICENSE
Requires-Dist: torch
Requires-Dist: einops (>=0.3)
